CHANGELOG.md
LICENSE
MANIFEST.in
NOTICE
README.md
pyproject.toml
setup.py
safe_radix32/__init__.py
safe_radix32/_cython.c
safe_radix32/_cython.pyx
safe_radix32/bytes.py
safe_radix32/pure.py
safe_radix32.egg-info/PKG-INFO
safe_radix32.egg-info/SOURCES.txt
safe_radix32.egg-info/dependency_links.txt
safe_radix32.egg-info/top_level.txt
tests/test_base.py
tests/test_bytes.py