Metadata-Version: 2.4
Name: safe_radix32
Version: 0.4.1
Summary: Radix32 with safe alphabet.
Author-email: Nándor Mátravölgyi <nandor.matra@gmail.com>
License-Expression: Apache-2.0
Project-URL: Repository, https://github.com/Traktormaster/safe-radix32/
Keywords: radix32,base32
Classifier: Operating System :: OS Independent
Classifier: Intended Audience :: Developers
Classifier: Programming Language :: Python :: Implementation :: CPython
Classifier: Programming Language :: Python :: Implementation :: PyPy
Requires-Python: >=3.9
License-File: LICENSE
License-File: NOTICE
Dynamic: license-file
